__init__.py
promptlite/__init__.py
promptlite/claude/__init__.py
promptlite/claude/coder.py
promptlite/claude/main.py
promptlite/language/__init__.py
promptlite/language/_python_coder.py
promptlite/personas/__init__.py
promptlite/personas/_ai_tech_lead_prompt.py
promptlite/personas/brainstrom_buddy.py
promptlite/reasoning/__init__.py
promptlite/reasoning/_predictive_reasoning.py
promptlite-1.2.0.dist-info/LICENSE
promptlite-1.2.0.dist-info/METADATA
promptlite-1.2.0.dist-info/WHEEL
promptlite-1.2.0.dist-info/top_level.txt
promptlite-1.2.0.dist-info/RECORD
